.coveragerc
.gitlab-ci.yml
LHCbProvisionRabbitMQ.sh
README.md
setup.py
lbmessaging/__init__.py
lbmessaging.egg-info/PKG-INFO
lbmessaging.egg-info/SOURCES.txt
lbmessaging.egg-info/dependency_links.txt
lbmessaging.egg-info/requires.txt
lbmessaging.egg-info/top_level.txt
lbmessaging/exchanges/CommandExchange.py
lbmessaging/exchanges/Common.py
lbmessaging/exchanges/ContinuousIntegrationExchange.py
lbmessaging/exchanges/CvmfsConDBExchange.py
lbmessaging/exchanges/CvmfsDevExchange.py
lbmessaging/exchanges/CvmfsProdExchange.py
lbmessaging/exchanges/PeriodicTestsExchange.py
lbmessaging/exchanges/__init__.py
lbmessaging/exchanges/test/__init__.py
lbmessaging/exchanges/test/test_TTL.py
lbmessaging/exchanges/test/test_admin.py
lbmessaging/exchanges/test/test_backwards_compat.py
lbmessaging/exchanges/test/test_command.py
lbmessaging/exchanges/test/test_consumer.py
lbmessaging/exchanges/test/test_continuous_integration_exchange.py
lbmessaging/exchanges/test/test_memory.py
lbmessaging/exchanges/test/test_periodic_tests.py
lbmessaging/exchanges/test/test_priority_levels.py
lbmessaging/exchanges/test/test_priority_queue.py
lbmessaging/exchanges/test/test_resend.py
lbmessaging/exchanges/test/test_rpc.py
lbmessaging/exchanges/test/test_signal.py
lbmessaging/exchanges/test/test_timeout.py
lbmessaging/services/CVMFSNightliesService.py
lbmessaging/services/Common.py
lbmessaging/services/LbCIService.py
lbmessaging/services/__init__.py
lbmessaging/services/test/__init__.py
lbmessaging/services/test/test_CVMFSNightliesService.py
lbmessaging/services/test/test_LbCIService.py
lbmessaging/services/test/test_expose_in.py
lbmessaging/services/test/test_meta_service.py